epubparser/main.py
epubparser-0.1.7.dist-info/LICENSE
epubparser-0.1.7.dist-info/METADATA
epubparser-0.1.7.dist-info/WHEEL
epubparser-0.1.7.dist-info/entry_points.txt
epubparser-0.1.7.dist-info/top_level.txt
epubparser-0.1.7.dist-info/RECORD
