Metadata-Version: 2.2
Name: epubparser
Version: 0.1.7
Summary: Parse ebooks, extracts chapters and contents.
Author: veralvx
Maintainer: veralvx
Project-URL: Homepage, https://github.com/veralvx/epubparser
Project-URL: Repository, https://github.com/veralvx/epubparser.git
Project-URL: Issues, https://github.com/veralvx/epubparser/issues
Project-URL: Mastodon, https://mastodon.social/@veralvx
Project-URL: Twitter, https://x.com/veralvx
Project-URL: Changelog, https://github.com/veralvx/epubparser/blob/main/CHANGELOG.md
Keywords: epub,ebook,conversion,filter
Classifier: Programming Language :: Python :: 3
Classifier: Programming Language :: Python :: 3.8
Classifier: Programming Language :: Python :: 3.9
Classifier: Programming Language :: Python :: 3.10
Classifier: Programming Language :: Python :: 3.11
Classifier: Programming Language :: Python :: 3.12
Classifier: Programming Language :: Python :: 3.13
Classifier: Programming Language :: Python :: 3.14
Classifier: Programming Language :: Python
Classifier: Environment :: Console
Classifier: Intended Audience :: Developers
Classifier: Topic :: Text Processing
Classifier: Topic :: Text Processing :: Filters
Classifier: Topic :: Text Processing :: General
Classifier: Topic :: Text Processing :: Markup :: XML
Classifier: Topic :: Text Processing :: Markup :: HTML
Classifier: Topic :: Text Processing :: Markup
Classifier: License :: OSI Approved :: MIT License
Classifier: Natural Language :: English
Requires-Python: >=3.8
License-File: LICENSE
Requires-Dist: ebooklib<0.20,>=0.18
